{"images": ["https://dai.fluidics.cc/1717779927347/OIG3.QINZRiaB2.xD.6ikxqpz?versionId=7e700c5659284940796c87868d6406f6", "https://dai.fluidics.cc/1717779927347/OIG3.LuAvZFBdTngScjFi3JyJ?versionId=7e700c5653d0055ba8bb38a4d8c857ef", "https://dai.fluidics.cc/1717779927347/OIG3.gOS7b363p57LUh9NEQYk?versionId=7e700c564f93bc4efa7ebd8882268005"], "content": "社下烧钱鼓似雷，日斜扶得醉翁回。", "origin": "春日田园杂兴", "author": "范成大", "category": "古诗文-天气-太阳", "date": "2024/6/8 01:05:27", "localImagesPath": "1717779927347"}