{"images": ["https://dai.fluidics.cc/1722035148461/OIG2.d.Vphee0zY8vXoc8T4wr?versionId=7e6f0eb4d131066d335bcefafdf3eec0", "https://dai.fluidics.cc/1722035148461/OIG2.biadZC4X9kYit8S_eQsP?versionId=7e6f0eb4c560eaa5fabea6e96bca4e55", "https://dai.fluidics.cc/1722035148461/OIG2.IYwrU83SPHM0fWouQYLe?versionId=7e6f0eb4bdb5f0076fb052a4f2c2ebbe", "https://dai.fluidics.cc/1722035148461/OIG2.9UabiUe1dHOXKk2ekZVm?versionId=7e6f0eb4b4fe341fb824745e233bd08a"], "content": "苦恨年年压金线，为他人作嫁衣裳。", "origin": "贫女", "author": "秦韬玉", "category": "古诗文-人物-女子", "date": "2024/7/27 07:05:48", "localImagesPath": "1722035148461"}