{"images": ["https://dai.fluidics.cc/1728774372802/OIG4.xcQtJBP3CJtQ9RhUVMa2?versionId=7e6d7d0469bbd655a42b212979f41354", "https://dai.fluidics.cc/1728774372802/OIG4.yYZ5H.UQ176abmiVG9Nn?versionId=7e6d7d04665f52dbce17140431e3da2f", "https://dai.fluidics.cc/1728774372802/OIG4.lHGvQRfxMXgNPScLtCNe?versionId=7e6d7d045f35b1b7c722c954cb685f71", "https://dai.fluidics.cc/1728774372802/OIG4.Inv4KQbEhC.ucUlAS1dA?versionId=7e6d7d0457cfb458119dcbbfc6ac670e"], "content": "岂知民力艰，颗米皆琳琅。", "origin": "秋日田家杂咏", "author": "黄燮清", "category": "古诗文-生活-田园", "date": "2024/10/13 07:06:12", "localImagesPath": "1728774372802"}